                 90 BUILD_CONST_KEY_MAP      4
                 92 STORE_NAME              13 (m)
     44          94 LOAD_CONST              22 (119)
                 96 LOAD_CONST              23 (116)
                 98 LOAD_CONST              24 (124)
                100 LOAD_CONST              25 (127)
                102 LOAD_CONST              26 ((3, 7, 9, 12))
                104 BUILD_CONST_KEY_MAP      4
                106 STORE_NAME              14 (n)
     45         108 LOAD_NAME               13 (m)
                110 LOAD_CONST              27 ( at 0x7f1199dd4c90, file "main.py", line 44>)
                112 LOAD_CONST              28 ('')
                114 MAKE_FUNCTION            0
                116 LOAD_NAME               14 (n)
                118 GET_ITER
                120 CALL_FUNCTION            1
                122 INPLACE_OR
                124 STORE_NAME              13 (m)
     47         126 LOAD_NAME               13 (m)
                128 LOAD_CONST              29 ( at 0x7f1199dd5b00, file "main.py", line 45>)
                130 LOAD_CONST              30 ('')
                132 MAKE_FUNCTION            0
                134 LOAD_NAME               10 (b)
                136 GET_ITER
                138 CALL_FUNCTION            1
                140 INPLACE_OR
                142 STORE_NAME              13 (m)
     48         144 LOAD_NAME                5 (RC4)
                146 LOAD_NAME               15 (list)
                148 LOAD_NAME               16 (map)
                150 LOAD_CONST              31 ( at 0x7f1199a42d90, file "main.py", line 47>)
                152 LOAD_CONST              32 ('')
                154 MAKE_FUNCTION            0
                156 LOAD_NAME               17 (sorted)
                158 LOAD_NAME               13 (m)
                160 LOAD_METHOD             18 (items)
                162 CALL_METHOD              0
                164 CALL_FUNCTION            1
                166 CALL_FUNCTION            2
                168 CALL_FUNCTION            1
                170 CALL_FUNCTION            1
                172 STORE_NAME              19 (stream)
     49         174 LOAD_NAME               20 (print)
                176 LOAD_NAME                6 (xor)
                178 LOAD_NAME                8 (w)
                180 LOAD_NAME               19 (stream)
                182 CALL_FUNCTION            2
                184 LOAD_METHOD             21 (decode)
                186 CALL_METHOD              0
                188 CALL_FUNCTION            1
                190 POP_TOP
     50         192 LOAD_NAME                0 (sys)
                194 LOAD_ATTR               22 (stdin)
                196 LOAD_ATTR               23 (buffer)
                198 LOAD_METHOD             24 (read)
                200 CALL_METHOD              0
                202 STORE_NAME              25 (p)
     52         204 LOAD_NAME                6 (xor)
                206 LOAD_NAME                9 (e)
                208 LOAD_NAME               19 (stream)
                210 CALL_FUNCTION            2
                212 STORE_NAME               9 (e)
     53         214 LOAD_NAME                6 (xor)
                216 LOAD_NAME               25 (p)
                218 LOAD_NAME               19 (stream)
                220 CALL_FUNCTION            2
                222 STORE_NAME              26 (c)
     54         224 LOAD_NAME                2 (sha256)
                226 LOAD_NAME               26 (c)
                228 CALL_FUNCTION            1
                230 LOAD_METHOD             27 (digest)
                232 CALL_METHOD              0
                234 LOAD_NAME               11 (s)
                236 COMPARE_OP               2 (==)
                238 POP_JUMP_IF_FALSE      131 (to 262)
     56         240 LOAD_NAME               20 (print)
                242 LOAD_NAME                6 (xor)
                244 LOAD_NAME               12 (t)
                246 LOAD_NAME               19 (stream)
                248 CALL_FUNCTION            2
                250 LOAD_METHOD             21 (decode)
                252 CALL_METHOD              0
                254 CALL_FUNCTION            1
                256 POP_TOP
                258 LOAD_CONST               1 (None)
                260 RETURN_VALUE
     33     >>  262 LOAD_NAME               20 (print)
                264 LOAD_NAME                9 (e)
                266 LOAD_METHOD             21 (decode)
                268 CALL_METHOD              0
                270 CALL_FUNCTION            1
                272 POP_TOP
                274 LOAD_CONST               1 (None)
                276 RETURN_VALUE
            >>  278 LOAD_CONST               1 (None)
                280 RETURN_VALUE
    Disassembly of :
      8           0 LOAD_GLOBAL              0 (len)
                  2 LOAD_FAST                0 (key)
                  4 CALL_FUNCTION            1
                  6 STORE_FAST               1 (keylength)
      9           8 LOAD_GLOBAL              1 (list)
                 10 LOAD_GLOBAL              2 (range)
                 12 LOAD_CONST               1 (256)
                 14 CALL_FUNCTION            1
                 16 CALL_FUNCTION            1
                 18 STORE_FAST               2 (S)
     10          20 LOAD_CONST               2 (0)
                 22 STORE_FAST               3 (j)
     11          24 LOAD_GLOBAL              2 (range)
                 26 LOAD_CONST               1 (256)
                 28 CALL_FUNCTION            1
                 30 GET_ITER
            >>   32 FOR_ITER                29 (to 92)
                 34 STORE_FAST               4 (i)
     12          36 LOAD_FAST                3 (j)
                 38 LOAD_FAST                2 (S)
                 40 LOAD_FAST                4 (i)
                 42 BINARY_SUBSCR
                 44 BINARY_ADD
                 46 LOAD_FAST                0 (key)
                 48 LOAD_FAST                4 (i)
                 50 LOAD_FAST                1 (keylength)
                 52 BINARY_MODULO
                 54 BINARY_SUBSCR
                 56 BINARY_ADD
                 58 LOAD_CONST               1 (256)
                 60 BINARY_MODULO
                 62 STORE_FAST               3 (j)
     13          64 LOAD_FAST                2 (S)
                 66 LOAD_FAST                3 (j)
                 68 BINARY_SUBSCR
                 70 LOAD_FAST                2 (S)
                 72 LOAD_FAST                4 (i)
                 74 BINARY_SUBSCR
                 76 ROT_TWO
                 78 LOAD_FAST                2 (S)
                 80 LOAD_FAST                4 (i)
                 82 STORE_SUBSCR
                 84 LOAD_FAST                2 (S)
                 86 LOAD_FAST                3 (j)
                 88 STORE_SUBSCR
                 90 JUMP_ABSOLUTE           16 (to 32)
            >>   92 LOAD_FAST                2 (S)
                 94 RETURN_VALUE
    Disassembly of :
     17           0 GEN_START                0
     18           2 LOAD_CONST               1 (0)
                  4 STORE_FAST               1 (i)
     19           6 LOAD_CONST               1 (0)
                  8 STORE_FAST               2 (j)
     20          10 NOP
     21     >>   12 LOAD_FAST                1 (i)
                 14 LOAD_CONST               3 (1)
                 16 BINARY_ADD
                 18 LOAD_CONST               4 (256)
                 20 BINARY_MODULO
                 22 STORE_FAST               1 (i)
     22          24 LOAD_FAST                2 (j)
                 26 LOAD_FAST                0 (S)
                 28 LOAD_FAST                1 (i)
                 30 BINARY_SUBSCR
                 32 BINARY_ADD
                 34 LOAD_CONST               4 (256)
                 36 BINARY_MODULO
                 38 STORE_FAST               2 (j)
     23          40 LOAD_FAST                0 (S)
                 42 LOAD_FAST                2 (j)
                 44 BINARY_SUBSCR
                 46 LOAD_FAST                0 (S)
                 48 LOAD_FAST                1 (i)
                 50 BINARY_SUBSCR
                 52 ROT_TWO
                 54 LOAD_FAST                0 (S)
                 56 LOAD_FAST                1 (i)
                 58 STORE_SUBSCR
                 60 LOAD_FAST                0 (S)
                 62 LOAD_FAST                2 (j)
                 64 STORE_SUBSCR
     24          66 LOAD_FAST                0 (S)
                 68 LOAD_FAST                0 (S)
                 70 LOAD_FAST                1 (i)
                 72 BINARY_SUBSCR
                 74 LOAD_FAST                0 (S)
                 76 LOAD_FAST                2 (j)
                 78 BINARY_SUBSCR
                 80 BINARY_ADD
                 82 LOAD_CONST               4 (256)
                 84 BINARY_MODULO
                 86 BINARY_SUBSCR
                 88 STORE_FAST               3 (K)
     19          90 LOAD_FAST                3 (K)
                 92 YIELD_VALUE
                 94 POP_TOP
                 96 JUMP_ABSOLUTE            6 (to 12)
    Disassembly of :
     28           0 LOAD_GLOBAL              0 (KSA)
                  2 LOAD_FAST                0 (key)
                  4 CALL_FUNCTION            1
                  6 STORE_FAST               1 (S)
                  8 LOAD_GLOBAL              1 (PRGA)
                 10 LOAD_FAST                1 (S)
                 12 CALL_FUNCTION            1
                 14 RETURN_VALUE
    Disassembly of :
     31           0 LOAD_GLOBAL              0 (bytes)
                  2 LOAD_GLOBAL              1 (map)
                  4 LOAD_CLOSURE             0 (stream)
                  6 BUILD_TUPLE              1
                  8 LOAD_CONST               1 ( at 0x7f1199dd5dc0, file "main.py", line 31>)
                 10 LOAD_CONST               2 ('xor..')
                 12 MAKE_FUNCTION            8 (closure)
                 14 LOAD_FAST                0 (p)
                 16 CALL_FUNCTION            2
                 18 CALL_FUNCTION            1
                 20 RETURN_VALUE
    Disassembly of  at 0x7f1199dd5dc0, file "main.py", line 31>: