为了提高文本的清晰度、连贯性和专业性，我将对这段字节码进行结构化和注释，以便更容易理解。以下是优化后的版本：

```python
# 生成常量键值映射并存储到变量 m 中
90   BUILD_CONST_KEY_MAP      4
92   STORE_NAME              13 (m)

# 加载常量并构建另一个常量键值映射，然后存储到变量 n 中
44   94   LOAD_CONST              22 (119)
       96   LOAD_CONST              23 (116)
       98   LOAD_CONST              24 (124)
      100   LOAD_CONST              25 (127)
      102   LOAD_CONST              26 ((3, 7, 9, 12))
      104   BUILD_CONST_KEY_MAP      4
      106   STORE_NAME              14 (n)

# 将 m 和一个函数的结果进行位或操作，并将结果存回 m
45   108  LOAD_NAME               13 (m)
      110  LOAD_CONST              27 ( at 0x7f1199dd4c90, file "main.py", line 44>)
      112  LOAD_CONST              28 ('')
      114  MAKE_FUNCTION            0
      116  LOAD_NAME               14 (n)
      118  GET_ITER
      120  CALL_FUNCTION            1
      122  INPLACE_OR
      124  STORE_NAME              13 (m)

# 再次将 m 和另一个函数的结果进行位或操作，并将结果存回 m
47   126  LOAD_NAME               13 (m)
      128  LOAD_CONST              29 ( at 0x7f1199dd5b00, file "main.py", line 45>)
      130  LOAD_CONST              30 ('')
      132  MAKE_FUNCTION            0
      134  LOAD_NAME               10 (b)
      136  GET_ITER
      138  CALL_FUNCTION            1
      140  INPLACE_OR
      142  STORE_NAME              13 (m)

# 调用 RC4 算法并存储结果到 stream
48   144  LOAD_NAME                5 (RC4)
      146  LOAD_NAME               15 (list)
      148  LOAD_NAME               16 (map)
      150  LOAD_CONST              31 ( at 0x7f1199a42d90, file "main.py", line 47>)
      152  LOAD_CONST              32 ('')
      154  MAKE_FUNCTION            0
      156  LOAD_NAME               17 (sorted)
      158  LOAD_NAME               13 (m)
      160  LOAD_METHOD             18 (items)
      162  CALL_METHOD              0
      164  CALL_FUNCTION            1
      166  CALL_FUNCTION            2
      168  CALL_FUNCTION            1
      170  CALL_FUNCTION            1
      172  STORE_NAME              19 (stream)

# 打印 xor 函数的结果
49   174  LOAD_NAME               20 (print)
      176  LOAD_NAME                6 (xor)
      178  LOAD_NAME                8 (w)
      180  LOAD_NAME               19 (stream)
      182  CALL_FUNCTION            2
      184  LOAD_METHOD             21 (decode)
      186  CALL_METHOD              0
      188  CALL_FUNCTION            1
      190  POP_TOP

# 从标准输入读取数据并存储到 p
50   192  LOAD_NAME                0 (sys)
      194  LOAD_ATTR               22 (stdin)
      196  LOAD_ATTR               23 (buffer)
      198  LOAD_METHOD             24 (read)
      200  CALL_METHOD              0
      202  STORE_NAME              25 (p)

# 对 e 和 stream 进行 xor 操作并将结果存回 e
52   204  LOAD_NAME                6 (xor)
      206  LOAD_NAME                9 (e)
      208  LOAD_NAME               19 (stream)
      210  CALL_FUNCTION            2
      212  STORE_NAME               9 (e)

# 对 p 和 stream 进行 xor 操作并将结果存回 c
53   214  LOAD_NAME                6 (xor)
      216  LOAD_NAME               25 (p)
      218  LOAD_NAME               19 (stream)
      220  CALL_FUNCTION            2
      222  STORE_NAME              26 (c)

# 计算 c 的 sha256 值并与 s 比较，如果相等则执行某些操作
54   224  LOAD_NAME                2 (sha256)
      226  LOAD_NAME               26 (c)
      228  CALL_FUNCTION            1
      230  LOAD_METHOD             27 (digest)
      232  CALL_METHOD              0
      234  LOAD_NAME               11 (s)
      236  COMPARE_OP               2 (==)
      238  POP_JUMP_IF_FALSE      131 (to 262)

# 如果比较结果为真，则打印解码后的 t 并返回 None
56   240  LOAD_NAME               20 (print)
      242  LOAD_NAME                6 (xor)
      244  LOAD_NAME               12 (t)
      246  LOAD_NAME               19 (stream)
      248  CALL_FUNCTION            2
      250  LOAD_METHOD             21 (decode)
      252  CALL_METHOD              0
      254  CALL_FUNCTION            1
      256  POP_TOP
      258  LOAD_CONST               1 (None)
      260  RETURN_VALUE

# 如果比较结果为假，则打印解码后的 e 并返回 None
33   262  LOAD_NAME               20 (print)
      264  LOAD_NAME                9 (e)
      266  LOAD_METHOD             21 (decode)
      268  CALL_METHOD              0
      270  CALL_FUNCTION            1
      272  POP_TOP
      274  LOAD_CONST               1 (None)
      276  RETURN_VALUE

# 返回 None
278  LOAD_CONST               1 (None)
280  RETURN_VALUE
```

### 解释
- **BUILD_CONST_KEY_MAP**：创建一个常量键值映射。
- **STORE_NAME**：将结果存储到指定的变量中。
- **LOAD_CONST**：加载常量。
- **MAKE_FUNCTION**：创建一个函数对象。
- **GET_ITER**：获取迭代器。
- **CALL_FUNCTION**：调用函数。
- **INPLACE_OR**：执行按位或操作。
- **LOAD_NAME**：加载名称（变量）。
- **LOAD_GLOBAL**：加载全局变量。
- **LOAD_METHOD**：加载方法。
- **CALL_METHOD**：调用方法。
- **POP_JUMP_IF_FALSE**：如果条件为假，则跳转到指定位置。
- **COMPARE_OP**：进行比较操作。
- **RETURN_VALUE**：返回值。

通过这种方式，可以更清晰地看到每一步的操作及其目的。