以下是优化后的文本，使其更加清晰、连贯和专业：

---

在分析字节码的过程中，我们注意到以下部分：

```
25 LOAD_CONST          5 (5)
28
29 STORE_GLOBAL        2 (2)
32 STORE_GLOBAL        1 (1)
35
36 STORE_GLOBAL        3 (3)
39
40 LOAD_CONST          6 (6)
43 PRINT_EXPR     
44
45 LOAD_CONST          5 (5)
48
49 STORE_GLOBAL        2 (2)
52 LOAD_CONST          6 (6)
55 PRINT_EXPR     
56
57 LOAD_CONST          7 (7)
60
61 STORE_FAST          4 (4)
64                0
67 DELETE_ATTR         1 (1)
70 STORE_GLOBAL        4 (4)
73 CALL_FUNCTION       1
76 STORE_FAST          5 (5)
79 STORE_GLOBAL        5 (5)
82 DELETE_ATTR         2 (2)
85 STORE_GLOBAL        0 (0)
88 CALL_FUNCTION       1
91 RETURN_VALUE 
```

继续分析发现代码执行出现问题。从底部开始重新分析：

```
64                0
67 DELETE_ATTR         1 (1)
70 STORE_GLOBAL        4 (4)
73 CALL_FUNCTION       1
76 STORE_FAST          5 (5)
79 STORE_GLOBAL        5 (5)
82 DELETE_ATTR         2 (2)
85 STORE_GLOBAL        0 (0)
88 CALL_FUNCTION       1
91 RETURN_VALUE
```

根据之前的结论，可以猜测这段代码是：
```python
xxx = rotor.newrotor(secret)
return xxx.decrypt(data)
```
因此，可以推测操作数如下：
- `0` 指的是局部变量 `data`
- `1` 指的是全局变量 `newrotor`
- `2` 可能是指全局变量 `decrypt`
- `4` 指的是局部变量 `secret`
- `5` 指的是局部变量 `rot`
- `0` 可能指的是全局变量 `rotor`

将字节码修改为：
```
64 LOAD_GLOBAL         0
67 LOAD_ATTR           1 (1)
70 LOAD_FAST           4 (4)
73 CALL_FUNCTION       1
76 STORE_FAST          5 (5)
79 LOAD_FAST           5 (5)
82 LOAD_ATTR           2 (2)
85 LOAD_FAST           0 (0)
88 CALL_FUNCTION       1
91 RETURN_VALUE
```

经过验证，这种修改是合理的。

整体替换字节码后，得到以下结果：
```python
>>> dis.disassemble_string(dec.co_code.replace("\x99","\x64").replace("\x68","\x7d").replace("\x61","\x7c").replace("\x60","\x6a").replace("\x9b","\x74"))
              0 LOAD_CONST          1 (1)
              3 STORE_FAST          1 (1)
              6 LOAD_CONST          2 (2)
              9 STORE_FAST          2 (2)
             12 LOAD_CONST          3 (3)
             15 STORE_FAST          3 (3)
             18 LOAD_FAST           1 (1)
             21 LOAD_CONST          4 (4)
             24 PRINT_EXPR     
             25 LOAD_CONST          5 (5)
             28            
             29 LOAD_FAST           2 (2)
             32 LOAD_FAST           1 (1)
             35            
             36 LOAD_FAST           3 (3)
             39            
             40 LOAD_CONST          6 (6)
             43 PRINT_EXPR     
             44            
             45 LOAD_CONST          5 (5)
             48            
             49 LOAD_FAST           2 (2)
             52 LOAD_CONST          6 (6)
             55 PRINT_EXPR     
             56            
             57 LOAD_CONST          7 (7)
             60            
             61 STORE_FAST          4 (4)
             64 LOAD_GLOBAL         0 (0)
             67 LOAD_ATTR           1 (1)
             70 LOAD_FAST           4 (4)
             73 CALL_FUNCTION       1
             76 STORE_FAST          5 (5)
             79 LOAD_FAST           5 (5)
             82 LOAD_ATTR           2 (2)
             85 LOAD_FAST           0 (0)
             88 CALL_FUNCTION       1
             91 RETURN_VALUE
             18 LOAD_FAST           1 (1)
             21 LOAD_CONST          4 (4)
             24 PRINT_EXPR     
             25 LOAD_CONST          5 (5)
             28            
             29 LOAD_FAST           2 (2)
             32 LOAD_FAST           1 (1)
             35            
             36 LOAD_FAST           3 (3)
             39            
             40 LOAD_CONST          6 (6)
             43 PRINT_EXPR     
             44            
             45 LOAD_CONST          5 (5)
             48            
             49 LOAD_FAST           2 (2)
             52 LOAD_CONST          6 (6)
             55 PRINT_EXPR     
             56            
             57 LOAD_CONST          7 (7)
             60            
             61 STORE_FAST          4 (4)
```

这部分代码可能是计算局部变量 `secret` 的方法，最后一句 `STORE_FAST 4` 将计算后的值存储到 `secret` 中。

通过进一步分析，发现主要的问题在于 `PRINT_EXPR` 和某些字符串操作。这些操作没有操作数，排除了调用函数或属性的可能性。考虑到最开始对 `key_a, key_b, key_c` 的赋值，且当前字节码中没有任何运算操作，可以推测 `PRINT_EXPR` 是字符串和整型之间的操作运算。

例如：
```python
             18 LOAD_FAST           1 ("!@#$%^&*")
             21 LOAD_CONST          4 (4)
             24 PRINT_EXPR
```

这里猜测 `PRINT_EXPR` 是字符串和整型之间的操作运算。

再来看这一部分：
```python
             29 LOAD_FAST           2 ("abcdefgh")
             32 LOAD_FAST           1 ("!@#$%^&*")
             35 
```

这里猜测 `LOAD_FAST` 是字符串和字符串之间的操作运算。

整型和字符串之间的操作可能包括：
- 字符串重复：`"a"*3`
- 字符串切片：`"aaa"[1]`, `"aaa"[:1]`, `"aaa"[1:]`

字符串和字符串之间的操作可能包括：
- 字符串拼接：`"aaa" + "bbb"`

综合以上分析，可以猜测 `LOAD_FAST` 是字符串拼接的操作，而 `PRINT_EXPR` 需要进一步尝试。最终，我们可以还原出 `decrypt` 函数：
```python
import rotor

def decrypt(data):
    key_a = "!@#$%^&*"
    key_b = "abcdefgh"
    key_c = '<>{}:"'
    secret = key_a * 4 + "|" + (key_b + key_a + key_c) * 2 + "|" + key_b * 2 + "EOF"
    rot = rotor.newrotor(secret)
    return rot.decrypt(data)
```

希望这个优化后的版本能够更清晰地展示整个分析过程。