            240 PRECALL                  1
            244 CALL                     1
            254 EXTENDED_ARG             4
            256 POP_JUMP_FORWARD_IF_FALSE  1094 (to 2446)
 32         258 LOAD_GLOBAL              1 (NULL + print)
            270 LOAD_FAST                3 (input)
            272 PRECALL                  1
            276 CALL                     1
            286 POP_TOP
 33         288 LOAD_FAST                0 (counterLines)
            290 LOAD_CONST               7 (1)
            292 BINARY_OP               13 (+=)
            296 STORE_FAST               0 (counterLines)
 35         298 LOAD_GLOBAL              1 (NULL + print)
            310 LOAD_CONST               8 ('- aGV5ISBJJ20gZ29pbmcgdG8gYXNrIHlvdSBhIGZldyByaWRkbGVzIGFuZCBpZiB5b3UgY2FuIHNvbHZlIHRoZW0gYWxsIEkgd2lsbCBnaXZlIHlvdSB0aGUgZmxhZyEgdG8gcHJvY2VlZCBqdXN0IHJlcGVhdCB0aGlzIG1lc3NhZ2Uu')
            312 PRECALL                  1
            316 CALL                     1
            326 POP_TOP
 36         328 LOAD_FAST                2 (lines)
            330 LOAD_CONST               7 (1)
            332 BINARY_SUBSCR
            342 LOAD_METHOD              4 (strip)
            364 PRECALL                  0
            368 CALL                     0
            378 LOAD_METHOD              5 (decode)
            400 LOAD_CONST               4 ('utf-8')
            402 LOAD_CONST               5 ('ignore')
            404 PRECALL                  2
            408 CALL                     2
            418 STORE_FAST               3 (input)
 37         420 LOAD_FAST                3 (input)
            422 LOAD_METHOD              6 (startswith)
            444 LOAD_CONST               9 ("hey! I'm going to ask you a few riddles and if you can solve them all I will give you the flag!")
            446 PRECALL                  1
            450 CALL                     1
            460 EXTENDED_ARG             3
            462 POP_JUMP_FORWARD_IF_FALSE   925 (to 2314)
 38         464 LOAD_GLOBAL              1 (NULL + print)
            476 LOAD_FAST                3 (input)
            478 PRECALL                  1
            482 CALL                     1
            492 POP_TOP
 39         494 LOAD_FAST                0 (counterLines)
            496 LOAD_CONST               7 (1)
            498 BINARY_OP               13 (+=)
            502 STORE_FAST               0 (counterLines)
 41         504 LOAD_GLOBAL              1 (NULL + print)
            516 LOAD_CONST              10 ("- Let's start easy...")
            518 PRECALL                  1
            522 CALL                     1
            532 POP_TOP
 42         534 LOAD_GLOBAL              1 (NULL + print)
            546 LOAD_CONST              11 ('- What is 2 + 2 = ?')
            548 PRECALL                  1
            552 CALL                     1
            562 POP_TOP
 43         564 LOAD_FAST                2 (lines)
            566 LOAD_CONST              12 (2)
            568 BINARY_SUBSCR
            578 LOAD_METHOD              4 (strip)
            600 PRECALL                  0
            604 CALL                     0
            614 LOAD_METHOD              5 (decode)
            636 LOAD_CONST               4 ('utf-8')
            638 LOAD_CONST               5 ('ignore')
            640 PRECALL                  2
            644 CALL                     2
            654 STORE_FAST               3 (input)
 44         656 LOAD_CONST              13 ('4')
            658 LOAD_FAST                3 (input)
            660 COMPARE_OP               2 (==)
            666 EXTENDED_ARG             2
            668 POP_JUMP_FORWARD_IF_FALSE   756 (to 2182)
 45         670 LOAD_GLOBAL              1 (NULL + print)
            682 LOAD_FAST                3 (input)
            684 PRECALL                  1
            688 CALL                     1
            698 POP_TOP
 46         700 LOAD_FAST                0 (counterLines)
            702 LOAD_CONST               7 (1)
            704 BINARY_OP               13 (+=)
            708 STORE_FAST               0 (counterLines)
 48         710 LOAD_GLOBAL              1 (NULL + print)
            722 LOAD_CONST              14 ("- Beep boop beep beep... I can't find my site on google! what am I missing?")
            724 PRECALL                  1
            728 CALL                     1
            738 POP_TOP
 49         740 LOAD_FAST                2 (lines)
            742 LOAD_CONST              15 (3)
            744 BINARY_SUBSCR
            754 LOAD_METHOD              4 (strip)
            776 PRECALL                  0
            780 CALL                     0
            790 LOAD_METHOD              5 (decode)
            812 LOAD_CONST               4 ('utf-8')
            814 LOAD_CONST               5 ('ignore')
            816 PRECALL                  2
            820 CALL                     2
            830 STORE_FAST               3 (input)
 50         832 LOAD_FAST                3 (input)
            834 LOAD_METHOD              6 (startswith)
            856 LOAD_CONST              16 ('robots')
            858 PRECALL                  1
            862 CALL                     1
            872 EXTENDED_ARG             2
            874 POP_JUMP_FORWARD_IF_FALSE   587 (to 2050)
 51         876 LOAD_GLOBAL              1 (NULL + print)
            888 LOAD_FAST                3 (input)
            890 PRECALL                  1
            894 CALL                     1
            904 POP_TOP
 52         906 LOAD_FAST                0 (counterLines)
            908 LOAD_CONST               7 (1)
            910 BINARY_OP               13 (+=)
            914 STORE_FAST               0 (counterLines)
 54         916 LOAD_GLOBAL              1 (NULL + print)
            928 LOAD_CONST              17 ('- What is null in ASCII?')
            930 PRECALL                  1
            934 CALL                     1
            944 POP_TOP
 55         946 LOAD_FAST                2 (lines)
            948 LOAD_CONST              18 (4)
            950 BINARY_SUBSCR
            960 LOAD_METHOD              4 (strip)
            982 PRECALL                  0
            986 CALL                     0
            996 LOAD_METHOD              5 (decode)
           1018 LOAD_CONST               4 ('utf-8')
           1020 LOAD_CONST               5 ('ignore')
           1022 PRECALL                  2
           1026 CALL                     2
           1036 STORE_FAST               3 (input)
 56        1038 LOAD_FAST                3 (input)
           1040 LOAD_METHOD              6 (startswith)
           1062 LOAD_CONST              19 ('0')
           1064 PRECALL                  1
           1068 CALL                     1
           1078 EXTENDED_ARG             1
           1080 POP_JUMP_FORWARD_IF_FALSE   417 (to 1916)
 57        1082 LOAD_GLOBAL              1 (NULL + print)
           1094 LOAD_CONST               1 (0)
           1096 PRECALL                  1
           1100 CALL                     1
           1110 POP_TOP
 58        1112 LOAD_FAST                0 (counterLines)
           1114 LOAD_CONST               7 (1)
           1116 BINARY_OP               13 (+=)
           1120 STORE_FAST               0 (counterLines)
 60        1122 LOAD_GLOBAL              1 (NULL + print)
           1134 LOAD_CONST              20 ('- Oh i know! just repeat what i say...')
           1136 PRECALL                  1
           1140 CALL                     1
           1150 POP_TOP
 61        1152 LOAD_GLOBAL              1 (NULL + print)
           1164 LOAD_CONST              21 ('- e99a18c428cb38d5f260853678922e03')
           1166 PRECALL                  1
           1170 CALL                     1
           1180 POP_TOP
 62        1182 LOAD_GLOBAL              1 (NULL + print)
           1194 LOAD_CONST              22 ("- You don't understand it? maybe you can ask john")
           1196 PRECALL                  1
           1200 CALL                     1
           1210 POP_TOP
 63        1212 LOAD_FAST                2 (lines)
           1214 LOAD_CONST              23 (5)
           1216 BINARY_SUBSCR
           1226 LOAD_METHOD              4 (strip)
           1248 PRECALL                  0
           1252 CALL                     0
           1262 LOAD_METHOD              5 (decode)
           1284 LOAD_CONST               4 ('utf-8')
           1286 LOAD_CONST               5 ('ignore')
           1288 PRECALL                  2
           1292 CALL                     2
           1302 STORE_FAST               3 (input)
 64        1304 LOAD_FAST                3 (input)
           1306 LOAD_METHOD              6 (startswith)
           1328 LOAD_CONST              24 ('abc123')
           1330 PRECALL                  1
           1334 CALL                     1
           1344 POP_JUMP_FORWARD_IF_FALSE   218 (to 1782)
 65        1346 LOAD_GLOBAL              1 (NULL + print)
           1358 LOAD_FAST                3 (input)
           1360 PRECALL                  1
           1364 CALL                     1
           1374 POP_TOP
 66        1376 LOAD_FAST                0 (counterLines)
           1378 LOAD_CONST               7 (1)
           1380 BINARY_OP               13 (+=)
           1384 STORE_FAST               0 (counterLines)
 68        1386 LOAD_GLOBAL              1 (NULL + print)
           1398 LOAD_CONST              25 ('- Finally just XOR !($+
As you can see, all the answers can be clearly seen inside. Of course, you'd still have the last riddle to solve yourself.